COPYING
COPYING.LESSER
MANIFEST.in
README.rst
setup.py
treacle/__init__.py
treacle/__main__.py
treacle/scrape_apple_ical.py
treacle/treacle.py
treacle.egg-info/PKG-INFO
treacle.egg-info/SOURCES.txt
treacle.egg-info/dependency_links.txt
treacle.egg-info/entry_points.txt
treacle.egg-info/not-zip-safe
treacle.egg-info/requires.txt
treacle.egg-info/top_level.txt
treacle/tests/__init__.py
treacle/tests/au_holidays_test.ics
treacle/tests/dtend_missing.ics
treacle/tests/partdays.ics
treacle/tests/sa_holidays_test.ics
treacle/tests/test_dtend_missing.py
treacle/tests/test_holidays.py
treacle/tests/test_partdays.py
treacle/tests/vic_holidays_test.ics