Metadata-Version: 1.1
Name: treacle
Version: 0.1.2
Summary: treacle is an AGI (Asterisk Gateway Interface) script which handles public holidays and opening hours in different offices with different timezones and different public holidays.
Home-page: https://github.com/Caramel/treacle
Author: Caramel
Author-email: support@caramel.com.au
License: LGPL3+
Platform: UNKNOWN
Classifier: License :: OSI Approved :: GNU Lesser General Public License v3 or later (LGPLv3+)
